similar_vid/__init__.py
similar_vid/loaders.py
similar_vid/matcher.py
similar_vid/similar_cli.py
similar_vid/similar_secs.py
similar_vid/tests/__init__.py
similar_vid/tests/tests.py
similar_vid-0.0.11.dist-info/LICENSE
similar_vid-0.0.11.dist-info/METADATA
similar_vid-0.0.11.dist-info/WHEEL
similar_vid-0.0.11.dist-info/top_level.txt
similar_vid-0.0.11.dist-info/RECORD
